{
  "Food": [
    "NOFRILLS", "NO FRILLS", "NOFILLS", "LOBLAWS", "METRO", "SOBEYS", "FRESHCO", "FOOD BASICS",
    "REAL CANADIAN SUPERSTORE", "SUPERSTORE", "WHOLE FOODS", "LONGOS",
    "COSTCO", "WALMART", "WAL-MART", "GIANT TIGER", "FARM BOY", "IGA", "SAFEWAY",
    "SAVE ON FOODS", "CO-OP", "WHOLESALE CLUB", "MAXI", "PROVIGO",
    "T&T", "H MART", "NATIONS", "OCEANS", "FOODLAND", "M&M FOOD",
    "TIM HORTONS", "MCDONALD", "A&W", "BURGER KING", "WENDYS",
    "SUBWAY", "PIZZA PIZZA", "DOMINOS", "PAPA JOHNS", "KFC",
    "HARVEYS", "SWISS CHALET", "SKIPTHEDISHES", "DOORDASH", "UBER EATS",
    "STARBUCKS", "SECOND CUP", "BOOSTER JUICE", "CHATIME", "DAVIDS TEA",
    "SUSHI", "RAMEN", "BBQ", "GRILL", "BAKERY", "CAFE", "RESTAURANT",
    "PIZZERIA", "PIZZA", "BURRITO", "TACO", "TAQUERIA", "SANDWICH",
    "DELI", "DINER", "BISTRO", "EATERY", "PUB", "POKE", "NOODLE"
  ],
  "Transport": [
    "PRESTO", "TTC", "GO TRANSIT", "MIWAY", "YRT", "OC TRANSPO",
    "UBER", "LYFT", "TAXI", "CAB", "AUTO", "PARKING",
    "ESSO", "SHELL", "PETRO", "PETROCAN", "CANADIAN TIRE GAS",
    "HUSKY", "ULTRAMAR", "CHEVRON", "FAS GAS", "CIRCLE K",
    "AIR CANADA", "WESTJET", "PORTER", "FLAIR", "AIRLINE",
    "VIA RAIL", "TRAIN", "BUS", "TRANSIT"
  ],
  "Utilities": [
    "HYDRO", "TORONTO HYDRO", "ENBRIDGE", "HYDRO ONE",
    "BC HYDRO", "FORTIS", "ATCO", "EPCOR",
    "ROGERS", "BELL", "TELUS", "FIDO", "KOODO", "VIRGIN",
    "SHAW", "FREEDOM", "VIDEOTRON", "SASKTEL",
    "INTERNET", "WIFI", "CABLE", "UTILITY"
  ],
  "Housing": [
    "RENT", "PROPERTY", "CONDO", "APARTMENT", "LEASE",
    "MORTGAGE", "STRATA", "MAINTENANCE", "HOA",
    "REALTY", "PROPERTY MANAGEMENT"
  ],
  "Pets": [
    "PETSMART", "PET VALU", "PETCO", "GLOBAL PET FOODS",
    "VET", "VETERINARY", "ANIMAL HOSPITAL", "DOG", "CAT",
    "DAYCARE", "CHILDCARE", "SCHOOL", "TUITION", "KIDS"
  ],
  "Entertainment": [
    "NETFLIX", "SPOTIFY", "DISNEY", "DISNEY+", "CRAVE",
    "AMAZON PRIME", "PRIME VIDEO", "APPLE.COM/BILL",
    "APPLE", "ITUNES", "GOOGLE", "YOUTUBE",
    "STEAM", "EPIC GAMES", "PLAYSTATION", "XBOX", "NINTENDO",
    "CINEPLEX", "MOVIE", "THEATRE", "TICKETMASTER",
    "EVENTBRITE", "CONCERT", "GYM", "FITNESS", "GOODLIFE",
    "LA FITNESS", "PLANET FITNESS"
  ],
  "Slush Fund": [
    "AMAZON", "EBAY", "ALIEXPRESS", "BEST BUY", "WALMART ONLINE",
    "CANADIAN TIRE", "HOME DEPOT", "LOWES", "RONA", "IKEA",
    "DOLLARAMA", "SHOPPERS", "LCBO", "BEER STORE",
    "INDIGO", "CHAPTERS", "HUDSONS BAY", "H&M", "ZARA",
    "UNIQLO", "NIKE", "ADIDAS", "FOOT LOCKER",
    "SEPHORA", "WINNERS", "MARSHALLS", "COSTCO ONLINE"
  ]
}
